task_progress_api
task_progress_handlers
